Metadata-Version: 1.1
Name: carotte
Version: 0.2.2
Summary: Carotte is a very lightweight Celery on zmq
Home-page: https://github.com/toxinu/carotte
Author: toxinu
Author-email: toxinu@gmail.com
License: The MIT License (MIT)
